messaging/__init__.py
messaging/client.py
messaging/example.py
messaging/exceptions.py
messaging/middleware.py
messaging/server.py
messaging/types.py
messaging/utils.py
dojo_messaging-1.0.15.dist-info/METADATA
dojo_messaging-1.0.15.dist-info/WHEEL
dojo_messaging-1.0.15.dist-info/top_level.txt
dojo_messaging-1.0.15.dist-info/RECORD
