Metadata-Version: 2.4
Name: dojo-messaging
Version: 1.0.15
Summary: Messaging utilities for dojo applications
Author-email: jarvis8x7b <jarvis@tensorplex.ai>
License: MIT
Project-URL: Homepage, https://github.com/pypa/dojo-messaging
Project-URL: Bug Reports, https://github.com/tensorplex-labs/dojo-messaging/issues
Project-URL: Source, https://github.com/tensorplex-labs/dojo-messaging
Keywords: messaging,dojo,async
Classifier: Development Status :: 3 - Alpha
Classifier: Intended Audience :: Developers
Classifier: Topic :: Software Development :: Build Tools
Classifier: License :: OSI Approved :: MIT License
Classifier: Programming Language :: Python :: 3
Classifier: Programming Language :: Python :: 3.11
Classifier: Programming Language :: Python :: 3.12
Classifier: Programming Language :: Python :: 3.13
Classifier: Programming Language :: Python :: 3 :: Only
Requires-Python: >=3.11
Requires-Dist: aiohttp~=3.10.11
Requires-Dist: httpx~=0.27.0
Requires-Dist: loguru~=0.7.2
Requires-Dist: orjson~=3.10.16
Requires-Dist: pydantic~=2.8.2
Requires-Dist: python-dotenv
Requires-Dist: tenacity~=8.5.0
Requires-Dist: uvicorn~=0.22.0
Requires-Dist: zstandard~=0.23.0
Requires-Dist: kami-client>=1.1.1
Provides-Extra: dev
Requires-Dist: pylint; extra == "dev"
Requires-Dist: ruff; extra == "dev"
Requires-Dist: pyright; extra == "dev"
